{
  "failure_count": 0,
  "last_failure_sha": "e5a8aa330bb86641d704d28da5782638cdda397a",
  "last_healed_sha": "ca5842928c4cad152a0ad074675c2baf38014d0d",
  "last_healed_at": "2026-07-02T05:29:06.074716+00:00",
  "history": [
    {
      "sha": "f0211ce765eaf891d59f90d9917bf45a6350ed06",
      "action": "PATCH",
      "healed": true,
      "timestamp": "2026-07-02T04:47:37.337984+00:00"
    },
    {
      "sha": "1596d5f5ec5838627c35b578c3613b0f2093bfd2",
      "action": "PATCH",
      "healed": false,
      "timestamp": "2026-07-02T05:07:23.252875+00:00"
    },
    {
      "sha": "86d306791d5780082a09da652c3da130bc7ea2e8",
      "action": "ROLLBACK",
      "healed": true,
      "timestamp": "2026-07-02T05:08:53.098531+00:00"
    },
    {
      "sha": "f0b20b1b2a13eceda3b6083473d11ebf633ca7ee",
      "action": "PATCH",
      "healed": false,
      "timestamp": "2026-07-02T05:12:41.408947+00:00"
    },
    {
      "sha": "df832411dbf7e8f21d60d46b73df29db75ceb674",
      "action": "PATCH",
      "healed": false,
      "timestamp": "2026-07-02T05:14:05.506691+00:00"
    },
    {
      "sha": "af40bb178289a900175f030809a1b2d30842596d",
      "action": "PATCH",
      "healed": false,
      "timestamp": "2026-07-02T05:15:39.367376+00:00"
    },
    {
      "sha": "df4dab30b733886023e049dece2e3c4b0947afad",
      "action": "PATCH",
      "healed": true,
      "timestamp": "2026-07-02T05:22:11.424156+00:00"
    },
    {
      "sha": "1ee0b2da5eda896b01cc5bacea1fe07281343fcb",
      "action": "PATCH",
      "healed": false,
      "timestamp": "2026-07-02T05:27:39.230157+00:00"
    },
    {
      "sha": "ca5842928c4cad152a0ad074675c2baf38014d0d",
      "action": "PATCH",
      "healed": true,
      "timestamp": "2026-07-02T05:29:06.074735+00:00"
    },
    {
      "sha": "49ad084f58b08914cdc9a702556768985935d6c5",
      "action": "PATCH",
      "healed": false,
      "timestamp": "2026-07-03T14:34:13.243414+00:00"
    },
    {
      "sha": "ef65d3edc23ba485931de4993908eba32ff19023",
      "action": "ROLLBACK",
      "healed": false,
      "timestamp": "2026-07-03T14:35:40.618525+00:00"
    },
    {
      "sha": "5d910186c1a7c7bbfff1994ca11b0307ccc19a76",
      "action": "ROLLBACK",
      "healed": false,
      "timestamp": "2026-07-03T14:50:55.798438+00:00"
    },
    {
      "sha": "3d8fd2038a3ee64ebca54ff289a4184d2c956762",
      "action": "PATCH",
      "healed": false,
      "timestamp": "2026-07-03T14:55:38.599365+00:00"
    },
    {
      "sha": "44e37de6e0d77efe842f9c366c06c7c30f7bfda2",
      "action": "PATCH",
      "healed": false,
      "timestamp": "2026-07-03T14:57:04.202895+00:00"
    },
    {
      "sha": "1feb79d53638ee6371d060e86f9eb229e5c644ef",
      "action": "PATCH",
      "healed": false,
      "timestamp": "2026-07-03T15:33:07.757656+00:00"
    },
    {
      "sha": "46001b51dcdaaf522cd107dcc77741b73fa66f44",
      "action": "PATCH",
      "healed": false,
      "timestamp": "2026-07-03T15:34:59.949402+00:00"
    },
    {
      "sha": "0362688e18b03b02ea08e9a24f3852ca910dfa77",
      "action": "ROLLBACK",
      "healed": false,
      "timestamp": "2026-07-03T15:36:31.820994+00:00"
    },
    {
      "sha": "166537b6ea76b0374fc99dbd4aa4a7682ccbdf04",
      "action": "PATCH",
      "healed": false,
      "timestamp": "2026-07-03T16:04:23.006073+00:00"
    },
    {
      "sha": "547accc20dcf9976a79547550de02d45613a454e",
      "action": "PATCH",
      "healed": false,
      "timestamp": "2026-07-03T16:06:09.455514+00:00"
    },
    {
      "sha": "e5a8aa330bb86641d704d28da5782638cdda397a",
      "action": "ROLLBACK",
      "healed": false,
      "timestamp": "2026-07-03T16:07:37.294025+00:00"
    }
  ]
}